<annotation>
	<folder>train</folder>
	<filename>IMG_0343JPG.jpg</filename>
	<path>C:\Users\gregt_000\Documents\phase10images\train\IMG_0343JPG.jpg</path>
	<source>
		<database>Unknown</database>
	</source>
	<size>
		<width>3024</width>
		<height>2256</height>
		<depth>3</depth>
	</size>
	<segmented>0</segmented>
	<object>
		<name>three</name>
		<pose>Unspecified</pose>
		<truncated>0</truncated>
		<difficult>0</difficult>
		<bndbox>
			<xmin>1356</xmin>
			<ymin>539</ymin>
			<xmax>2304</xmax>
			<ymax>1455</ymax>
		</bndbox>
	</object>
	<object>
		<name>six</name>
		<pose>Unspecified</pose>
		<truncated>0</truncated>
		<difficult>0</difficult>
		<bndbox>
			<xmin>1261</xmin>
			<ymin>1548</ymin>
			<xmax>2199</xmax>
			<ymax>2234</ymax>
		</bndbox>
	</object>
	<object>
		<name>two</name>
		<pose>Unspecified</pose>
		<truncated>1</truncated>
		<difficult>0</difficult>
		<bndbox>
			<xmin>1</xmin>
			<ymin>98</ymin>
			<xmax>1002</xmax>
			<ymax>855</ymax>
		</bndbox>
	</object>
	<object>
		<name>one</name>
		<pose>Unspecified</pose>
		<truncated>1</truncated>
		<difficult>0</difficult>
		<bndbox>
			<xmin>2379</xmin>
			<ymin>793</ymin>
			<xmax>3024</xmax>
			<ymax>1623</ymax>
		</bndbox>
	</object>
</annotation>
