<annotation>
	<folder>test</folder>
	<filename>IMG_0187JPG.jpg</filename>
	<path>C:\Users\gregt_000\Documents\phase10images\test\IMG_0187JPG.jpg</path>
	<source>
		<database>Unknown</database>
	</source>
	<size>
		<width>1504</width>
		<height>2016</height>
		<depth>3</depth>
	</size>
	<segmented>0</segmented>
	<object>
		<name>eight</name>
		<pose>Unspecified</pose>
		<truncated>0</truncated>
		<difficult>0</difficult>
		<bndbox>
			<xmin>613</xmin>
			<ymin>962</ymin>
			<xmax>1015</xmax>
			<ymax>1526</ymax>
		</bndbox>
	</object>
	<object>
		<name>ten</name>
		<pose>Unspecified</pose>
		<truncated>0</truncated>
		<difficult>0</difficult>
		<bndbox>
			<xmin>501</xmin>
			<ymin>98</ymin>
			<xmax>909</xmax>
			<ymax>706</ymax>
		</bndbox>
	</object>
	<object>
		<name>three</name>
		<pose>Unspecified</pose>
		<truncated>0</truncated>
		<difficult>0</difficult>
		<bndbox>
			<xmin>3</xmin>
			<ymin>412</ymin>
			<xmax>507</xmax>
			<ymax>1070</ymax>
		</bndbox>
	</object>
</annotation>
