<annotation>
	<folder>train</folder>
	<filename>IMG_0130.jpg</filename>
	<path>C:\tensorflow1\models\research\object_detection\images\train\IMG_0130.jpg</path>
	<source>
		<database>Unknown</database>
	</source>
	<size>
		<width>720</width>
		<height>1280</height>
		<depth>3</depth>
	</size>
	<segmented>0</segmented>
	<object>
		<name>eleven</name>
		<pose>Unspecified</pose>
		<truncated>0</truncated>
		<difficult>0</difficult>
		<bndbox>
			<xmin>180</xmin>
			<ymin>535</ymin>
			<xmax>372</xmax>
			<ymax>839</ymax>
		</bndbox>
	</object>
</annotation>
