<annotation>
	<folder>train</folder>
	<filename>IMG_0347JPG.jpg</filename>
	<path>C:\Users\gregt_000\Documents\phase10images\train\IMG_0347JPG.jpg</path>
	<source>
		<database>Unknown</database>
	</source>
	<size>
		<width>3024</width>
		<height>2256</height>
		<depth>3</depth>
	</size>
	<segmented>0</segmented>
	<object>
		<name>one</name>
		<pose>Unspecified</pose>
		<truncated>0</truncated>
		<difficult>0</difficult>
		<bndbox>
			<xmin>747</xmin>
			<ymin>573</ymin>
			<xmax>1336</xmax>
			<ymax>1250</ymax>
		</bndbox>
	</object>
	<object>
		<name>nine</name>
		<pose>Unspecified</pose>
		<truncated>0</truncated>
		<difficult>0</difficult>
		<bndbox>
			<xmin>1540</xmin>
			<ymin>830</ymin>
			<xmax>2149</xmax>
			<ymax>1318</ymax>
		</bndbox>
	</object>
	<object>
		<name>six</name>
		<pose>Unspecified</pose>
		<truncated>0</truncated>
		<difficult>0</difficult>
		<bndbox>
			<xmin>2415</xmin>
			<ymin>523</ymin>
			<xmax>2977</xmax>
			<ymax>1166</ymax>
		</bndbox>
	</object>
	<object>
		<name>three</name>
		<pose>Unspecified</pose>
		<truncated>0</truncated>
		<difficult>0</difficult>
		<bndbox>
			<xmin>1554</xmin>
			<ymin>1482</ymin>
			<xmax>2097</xmax>
			<ymax>1839</ymax>
		</bndbox>
	</object>
	<object>
		<name>four]</name>
		<pose>Unspecified</pose>
		<truncated>0</truncated>
		<difficult>0</difficult>
		<bndbox>
			<xmin>374</xmin>
			<ymin>1255</ymin>
			<xmax>1077</xmax>
			<ymax>1852</ymax>
		</bndbox>
	</object>
	<object>
		<name>three</name>
		<pose>Unspecified</pose>
		<truncated>0</truncated>
		<difficult>0</difficult>
		<bndbox>
			<xmin>81</xmin>
			<ymin>55</ymin>
			<xmax>806</xmax>
			<ymax>543</ymax>
		</bndbox>
	</object>
	<object>
		<name>nine</name>
		<pose>Unspecified</pose>
		<truncated>0</truncated>
		<difficult>0</difficult>
		<bndbox>
			<xmin>2513</xmin>
			<ymin>1480</ymin>
			<xmax>3006</xmax>
			<ymax>2039</ymax>
		</bndbox>
	</object>
</annotation>
